nats_bootstrap/__init__.py
nats_bootstrap/__main__.py
nats_bootstrap/bootstrap_config.py
nats_bootstrap/cli.py
nats_bootstrap/config.py
nats_bootstrap/controller.py
nats_bootstrap/controller_client.py
nats_bootstrap/nats_cli.py
nats_bootstrap/resolve.py
nats_bootstrap/service_windows.py
nats_bootstrap-0.0.9.dist-info/licenses/LICENSE
nats_bootstrap-0.0.9.dist-info/METADATA
nats_bootstrap-0.0.9.dist-info/WHEEL
nats_bootstrap-0.0.9.dist-info/entry_points.txt
nats_bootstrap-0.0.9.dist-info/top_level.txt
nats_bootstrap-0.0.9.dist-info/RECORD
