Metadata-Version: 2.4
Name: nats-bootstrap
Version: 0.0.9
Summary: Super simple CLI to bootstrap and manage NATS clusters.
Requires-Python: >=3.10
License-File: LICENSE
Provides-Extra: server
Requires-Dist: nats-server-bin; extra == "server"
Dynamic: license-file
